{
    "Dog": {
        "Rabies 1-year":{
            "U16W": {},
            "O16W": {
                "InitVac":[0, 1],
                "BoostVac":[[52, 0]]
            }
        },
        "Rabies 3-year":{
            "InitVac":[0, 1],
            "BoostVac":[[52, 1], [156, 0]]
        },
        "Distemper":{
            "U16W": {},
            "O16W": {
                "InitVac":,
                "BoostVac":
            }
        },
        "Parvovirus":{
            "U16W": {},
            "O16W": {
                "InitVac":,
                "BoostVac":
            }
        },
        "Adenovirus, type 1 (CAV-1, canine hepatitis)":{
            "U16W": {},
            "O16W": {
                "InitVac":,
                "BoostVac":
            }
        },
        "Adenovirus, type 2 (CAV-2, kennel cough)":{
            "U16W": {},
            "O16W": {
                "InitVac":,
                "BoostVac":
            }
        },
        "Parainfluenza":{
            "U16W": {},
            "O16W": {
                "InitVac":,
                "BoostVac":
            }
        },
        "Bordetella bronchiseptica (kennel cough)":{
            "U16W": {},
            "O16W": {
                "InitVac":,
                "BoostVac":
            }
        },
        "Lyme disease":{
            "U16W": {},
            "O16W": {
                "InitVac":,
                "BoostVac":
            }
        },
        "Leptospirosis":{
            "U16W": {},
            "O16W": {
                "InitVac":,
                "BoostVac":
            }
        },
        "Canine influenza":{
            "U16W": {},
            "O16W": {
                "InitVac":,
                "BoostVac":
            }
        }
    },
    "Cat": {

    }
}